dagster_dg_cli/__init__.py
dagster_dg_cli/py.typed
dagster_dg_cli/scaffold.py
dagster_dg_cli/version.py
dagster_dg_cli/api_layer/__init__.py
dagster_dg_cli/api_layer/api/__init__.py
dagster_dg_cli/api_layer/api/agent.py
dagster_dg_cli/api_layer/api/asset.py
dagster_dg_cli/api_layer/api/deployments.py
dagster_dg_cli/api_layer/api/run.py
dagster_dg_cli/api_layer/api/run_event.py
dagster_dg_cli/api_layer/api/schedule.py
dagster_dg_cli/api_layer/api/secret.py
dagster_dg_cli/api_layer/api/sensor.py
dagster_dg_cli/api_layer/graphql_adapter/__init__.py
dagster_dg_cli/api_layer/graphql_adapter/agent.py
dagster_dg_cli/api_layer/graphql_adapter/asset.py
dagster_dg_cli/api_layer/graphql_adapter/deployment.py
dagster_dg_cli/api_layer/graphql_adapter/run.py
dagster_dg_cli/api_layer/graphql_adapter/run_event.py
dagster_dg_cli/api_layer/graphql_adapter/schedule.py
dagster_dg_cli/api_layer/graphql_adapter/secret.py
dagster_dg_cli/api_layer/graphql_adapter/sensor.py
dagster_dg_cli/api_layer/schemas/__init__.py
dagster_dg_cli/api_layer/schemas/agent.py
dagster_dg_cli/api_layer/schemas/asset.py
dagster_dg_cli/api_layer/schemas/deployment.py
dagster_dg_cli/api_layer/schemas/run.py
dagster_dg_cli/api_layer/schemas/run_event.py
dagster_dg_cli/api_layer/schemas/schedule.py
dagster_dg_cli/api_layer/schemas/secret.py
dagster_dg_cli/api_layer/schemas/sensor.py
dagster_dg_cli/cli/__init__.py
dagster_dg_cli/cli/__main__.py
dagster_dg_cli/cli/check.py
dagster_dg_cli/cli/defs_state.py
dagster_dg_cli/cli/dev.py
dagster_dg_cli/cli/entrypoint.py
dagster_dg_cli/cli/launch.py
dagster_dg_cli/cli/list.py
dagster_dg_cli/cli/mcp_server.py
dagster_dg_cli/cli/utils.py
dagster_dg_cli/cli/api/__init__.py
dagster_dg_cli/cli/api/agent.py
dagster_dg_cli/cli/api/asset.py
dagster_dg_cli/cli/api/cli_group.py
dagster_dg_cli/cli/api/client.py
dagster_dg_cli/cli/api/deployment.py
dagster_dg_cli/cli/api/formatters.py
dagster_dg_cli/cli/api/log.py
dagster_dg_cli/cli/api/run.py
dagster_dg_cli/cli/api/run_event.py
dagster_dg_cli-1.12.13.dist-info/licenses/LICENSE
dagster_dg_cli-1.12.13.dist-info/METADATA
dagster_dg_cli-1.12.13.dist-info/WHEEL
dagster_dg_cli-1.12.13.dist-info/entry_points.txt
dagster_dg_cli-1.12.13.dist-info/top_level.txt
dagster_dg_cli-1.12.13.dist-info/RECORD
