Metadata-Version: 2.4
Name: dagster-dg-cli
Version: 1.12.13
Home-page: https://github.com/dagster-io/dagster/tree/master/python_modules/libraries/dagster-dg-cli
Author: Dagster Labs
Author-email: hello@dagsterlabs.com
License: Apache-2.0
Classifier: Programming Language :: Python :: 3.10
Classifier: Programming Language :: Python :: 3.11
Classifier: Programming Language :: Python :: 3.12
Classifier: Programming Language :: Python :: 3.13
Classifier: Programming Language :: Python :: 3.14
Classifier: License :: OSI Approved :: Apache Software License
Classifier: Operating System :: OS Independent
License-File: LICENSE
Requires-Dist: dagster-dg-core==1.12.13
Requires-Dist: dagster==1.12.13
Requires-Dist: dagster-cloud-cli==1.12.13
Requires-Dist: typer
Provides-Extra: test
Requires-Dist: syrupy>=4.0.0; extra == "test"
Provides-Extra: ai
Requires-Dist: anthropic; python_version >= "3.10" and extra == "ai"
Requires-Dist: claude-code-sdk>=0.0.19; python_version >= "3.10" and extra == "ai"
Requires-Dist: mcp; python_version >= "3.10" and extra == "ai"
Dynamic: author
Dynamic: author-email
Dynamic: classifier
Dynamic: home-page
Dynamic: license
Dynamic: license-file
Dynamic: provides-extra
Dynamic: requires-dist
